Metadata-Version: 2.1
Name: scikit-info
Version: 0.4.0
Summary: Scipy-styled expansion for information theory.
Home-page: UNKNOWN
Author: Mirko Mälicke
Author-email: mirko.maelicke@kit.edu
License: MIT
Platform: UNKNOWN
